CHANGES.rst
CONTRIBUTORS.rst
MANIFEST.in
README.rst
bootstrap.py
buildout.cfg
setup.py
cpskin/__init__.py
cpskin.diazotheme.vicinity.egg-info/PKG-INFO
cpskin.diazotheme.vicinity.egg-info/SOURCES.txt
cpskin.diazotheme.vicinity.egg-info/dependency_links.txt
cpskin.diazotheme.vicinity.egg-info/entry_points.txt
cpskin.diazotheme.vicinity.egg-info/namespace_packages.txt
cpskin.diazotheme.vicinity.egg-info/not-zip-safe
cpskin.diazotheme.vicinity.egg-info/requires.txt
cpskin.diazotheme.vicinity.egg-info/top_level.txt
cpskin/diazotheme/__init__.py
cpskin/diazotheme/vicinity/__init__.py
cpskin/diazotheme/vicinity/configure.zcml
cpskin/diazotheme/vicinity/profiles.zcml
cpskin/diazotheme/vicinity/profiles/default/cssregistry.xml
cpskin/diazotheme/vicinity/profiles/default/lessregistry.xml
cpskin/diazotheme/vicinity/profiles/default/metadata.xml
cpskin/diazotheme/vicinity/profiles/default/theme.xml
cpskin/diazotheme/vicinity/profiles/uninstall/cssregistry.xml
cpskin/diazotheme/vicinity/profiles/uninstall/lessregistry.xml
cpskin/diazotheme/vicinity/static/manifest.cfg
cpskin/diazotheme/vicinity/static/preview.png
cpskin/diazotheme/vicinity/static/rules.xml
cpskin/diazotheme/vicinity/static/css/styles.css
cpskin/diazotheme/vicinity/static/images/acces_bg.png
cpskin/diazotheme/vicinity/static/images/agenda_bg.png
cpskin/diazotheme/vicinity/static/images/agenda_next.png
cpskin/diazotheme/vicinity/static/images/agenda_previous.png
cpskin/diazotheme/vicinity/static/images/compte.png
cpskin/diazotheme/vicinity/static/images/guichet.png
cpskin/diazotheme/vicinity/static/images/je-suis.png
cpskin/diazotheme/vicinity/static/images/je-trouve.png
cpskin/diazotheme/vicinity/static/images/menu_bg.png
cpskin/diazotheme/vicinity/static/images/plus_big.png
cpskin/diazotheme/vicinity/static/images/plus_small.png
cpskin/diazotheme/vicinity/static/images/plus_xsmall.png
cpskin/diazotheme/vicinity/static/images/slideshow_next.png
cpskin/diazotheme/vicinity/static/images/slideshow_previous.png
cpskin/diazotheme/vicinity/static/images/video_play_big.png
cpskin/diazotheme/vicinity/static/less/mobile.less
cpskin/diazotheme/vicinity/static/less/mobilelarge.less
cpskin/diazotheme/vicinity/static/less/styles.less
cpskin/diazotheme/vicinity/static/less/variables.less
cpskin/diazotheme/vicinity/static/rules/footer.xml
cpskin/diazotheme/vicinity/static/rules/header.xml
